hero/extensions/devtools/__init__.py
hero/extensions/devtools/cogs.py
hero/extensions/devtools/controller.py
discord_hero_devtools-0.1.0a0.dist-info/LICENSE
discord_hero_devtools-0.1.0a0.dist-info/LICENSE.Apache-2.0
discord_hero_devtools-0.1.0a0.dist-info/LICENSE.MIT
discord_hero_devtools-0.1.0a0.dist-info/METADATA
discord_hero_devtools-0.1.0a0.dist-info/WHEEL
discord_hero_devtools-0.1.0a0.dist-info/top_level.txt
discord_hero_devtools-0.1.0a0.dist-info/RECORD
