Metadata-Version: 2.1
Name: discord-hero-devtools
Version: 0.1.0a0
Summary: Discord Hero Developer Tools is a Debugging and Experimenting extension for Discord Hero. You can load, reload and unload extensions.
Home-page: https://github.com/discord-hero/discord-hero-devtools
Author: EraseKesu
Author-email: eitan.olchik@gmail.com
License: Apache-2.0 OR MIT
Keywords: discord-hero devtools discord bot
Platform: UNKNOWN
Classifier: Development Status :: 4 - Beta
Classifier: Environment :: Plugins
Classifier: Framework :: AsyncIO
Classifier: Intended Audience :: Developers
Classifier: Intended Audience :: End Users/Desktop
Classifier: License :: OSI Approved :: Apache Software License
Classifier: License :: OSI Approved :: MIT License
Classifier: Natural Language :: English
Classifier: Operating System :: OS Independent
Classifier: Programming Language :: Python
Classifier: Programming Language :: Python :: 3
Classifier: Programming Language :: Python :: 3 :: Only
Classifier: Programming Language :: Python :: 3.7
Classifier: Programming Language :: Python :: 3.8
Classifier: Topic :: Communications :: Chat
Classifier: Topic :: Software Development :: Libraries :: Python Modules
Requires-Python: >= 3.7.0
Requires-Dist: discord-hero (>=0.1.0b0)
